own_blockchain_sdk/__init__.py
own_blockchain_sdk/crypto.py
own_blockchain_sdk/test_crypto.py
own_blockchain_sdk/test_transactions.py
own_blockchain_sdk/transactions.py
own_blockchain_sdk-1.0.1.dist-info/LICENSE
own_blockchain_sdk-1.0.1.dist-info/METADATA
own_blockchain_sdk-1.0.1.dist-info/WHEEL
own_blockchain_sdk-1.0.1.dist-info/top_level.txt
own_blockchain_sdk-1.0.1.dist-info/RECORD
