Metadata-Version: 2.1
Name: own-blockchain-sdk
Version: 1.0.1
Summary: Own Blockchain SDK for Python
Home-page: https://github.com/OwnMarket/OwnBlockchainSdkPython
Author: Marian Gheorghe
Author-email: marian.gheorghe@weown.com
License: UNKNOWN
Platform: UNKNOWN
Classifier: Programming Language :: Python :: 3
Classifier: License :: OSI Approved :: MIT License
Classifier: Operating System :: OS Independent
